quantfeat/__init__.py
quantfeat/convert_data.py
quantfeat/eda.py
quantfeat/returns.py
quantfeat/validate.py
quantfeat/volatility.py
quantfeat-0.1.0.dist-info/METADATA
quantfeat-0.1.0.dist-info/WHEEL
quantfeat-0.1.0.dist-info/top_level.txt
quantfeat-0.1.0.dist-info/RECORD
