Metadata-Version: 2.4
Name: quantfeat
Version: 0.1.0
Summary: A data analytics, feature engineering library for time series price data
Author: Srisha KS
Author-email: Srisha KS <srishaks6@gmail.com>
Classifier: Programming Language :: Python :: 3
Classifier: License :: OSI Approved :: MIT License
Classifier: Operating System :: OS Independent
Classifier: Topic :: Scientific/Engineering :: Information Analysis
Requires-Python: >=3.8
Requires-Dist: pandas
Requires-Dist: numpy
Requires-Dist: seaborn
Requires-Dist: matplotlib
Requires-Dist: scipy
Dynamic: author
Dynamic: requires-python
